secml_torch-1.3.data/data/src/secmlt/VERSION/VERSION
secml_torch-1.3.dist-info/licenses/LICENSE
secmlt/VERSION
secmlt/__init__.py
secmlt/adv/__init__.py
secmlt/adv/backends.py
secmlt/adv/evasion/__init__.py
secmlt/adv/evasion/base_evasion_attack.py
secmlt/adv/evasion/fmn.py
secmlt/adv/evasion/perturbation_models.py
secmlt/adv/evasion/pgd.py
secmlt/adv/evasion/advlib_attacks/__init__.py
secmlt/adv/evasion/advlib_attacks/advlib_base.py
secmlt/adv/evasion/advlib_attacks/advlib_fmn.py
secmlt/adv/evasion/advlib_attacks/advlib_pgd.py
secmlt/adv/evasion/aggregators/__init__.py
secmlt/adv/evasion/aggregators/ensemble.py
secmlt/adv/evasion/foolbox_attacks/__init__.py
secmlt/adv/evasion/foolbox_attacks/foolbox_base.py
secmlt/adv/evasion/foolbox_attacks/foolbox_fmn.py
secmlt/adv/evasion/foolbox_attacks/foolbox_pgd.py
secmlt/adv/evasion/modular_attacks/__init__.py
secmlt/adv/evasion/modular_attacks/eot_gradient.py
secmlt/adv/evasion/modular_attacks/modular_attack.py
secmlt/adv/evasion/modular_attacks/modular_attack_fixed_eps.py
secmlt/adv/evasion/modular_attacks/modular_attack_min_distance.py
secmlt/adv/poisoning/__init__.py
secmlt/adv/poisoning/backdoor.py
secmlt/adv/poisoning/base_data_poisoning.py
secmlt/data/__init__.py
secmlt/data/distributions.py
secmlt/data/lp_uniform_sampling.py
secmlt/manipulations/__init__.py
secmlt/manipulations/manipulation.py
secmlt/metrics/__init__.py
secmlt/metrics/classification.py
secmlt/models/__init__.py
secmlt/models/base_model.py
secmlt/models/base_trainer.py
secmlt/models/data_processing/__init__.py
secmlt/models/data_processing/data_processing.py
secmlt/models/data_processing/identity_data_processing.py
secmlt/models/pytorch/__init__.py
secmlt/models/pytorch/base_pytorch_nn.py
secmlt/models/pytorch/base_pytorch_trainer.py
secmlt/optimization/__init__.py
secmlt/optimization/constraints.py
secmlt/optimization/gradient_processing.py
secmlt/optimization/initializer.py
secmlt/optimization/losses.py
secmlt/optimization/optimizer_factory.py
secmlt/optimization/random_perturb.py
secml_torch-1.3.dist-info/METADATA
secml_torch-1.3.dist-info/WHEEL
secml_torch-1.3.dist-info/top_level.txt
secml_torch-1.3.dist-info/RECORD
