Metadata-Version: 2.4
Name: secml-torch
Version: 1.3
Summary: SecML-Torch Library
Home-page: https://secml-torch.readthedocs.io/en/latest/
Author: Maura Pintor, Luca Demetrio
Author-email: maura.pintor@unica.it, luca.demetrio@unige.it
License: MIT
Classifier: Development Status :: 3 - Alpha
Classifier: Intended Audience :: Science/Research
Classifier: Intended Audience :: Developers
Classifier: License :: OSI Approved
Classifier: Programming Language :: Python
Classifier: Programming Language :: Python :: 3
Classifier: Programming Language :: Python :: 3.6
Classifier: Programming Language :: Python :: 3.7
Classifier: Programming Language :: Python :: 3.8
Classifier: Programming Language :: Python :: 3.9
Classifier: Programming Language :: Python :: 3.10
Classifier: Programming Language :: Python :: Implementation :: PyPy
Classifier: Topic :: Software Development
Classifier: Topic :: Scientific/Engineering
Requires-Python: >=3.7
License-File: LICENSE
Requires-Dist: torch!=1.5.*,>=1.4
Requires-Dist: torchvision!=0.6.*,>=0.5
Provides-Extra: foolbox
Requires-Dist: foolbox>=3.3.0; extra == "foolbox"
Provides-Extra: tensorboard
Requires-Dist: tensorboard; extra == "tensorboard"
Provides-Extra: adv-lib
Requires-Dist: adv_lib; extra == "adv-lib"
Dynamic: author
Dynamic: author-email
Dynamic: classifier
Dynamic: description
Dynamic: description-content-type
Dynamic: home-page
Dynamic: license
Dynamic: license-file
Dynamic: provides-extra
Dynamic: requires-dist
Dynamic: requires-python
Dynamic: summary
